plateforme/__init__.py
plateforme-0.0.0.dist-info/LICENSE
plateforme-0.0.0.dist-info/METADATA
plateforme-0.0.0.dist-info/WHEEL
plateforme-0.0.0.dist-info/top_level.txt
plateforme-0.0.0.dist-info/RECORD
